{
    "partList": [
        {
            "uuid": "7cf717d7-d167-4f2d-a6e7-6b2c70aa3986",
            "name": "obj_interactive_switch",
            "legacyId": 109,
            "renderable": "$CONTENT_DATA/Objects/Renderable/Interactive/obj_interactive_button.rend",
            "color": "df7f01",
            "hull": {
                "x": 1,
                "y": 1,
                "z": 1,
                "col": "$GAME_DATA/Objects/Collision/obj_interactive_button.obj"
            },
            "lever": {},
            "rotationSet": "PropY",
            "sticky": "-Y",
            "physicsMaterial": "Mechanical",
            "ratings": {
                "density": 2,
                "durability": 3,
                "friction": 5,
                "buoyancy": 2
            },
            "flammable": true,
            "stackSize": 10
        }
    ]
}